Metadata-Version: 1.1
Name: svyn
Version: 0.1.2
Summary: Convenience functions for svn
Home-page: https://github.com/ClockworkNet/svyn
Author: Lance T. Erickson
Author-email: lancetarn@gmail.com
License: MIT
Platform: UNKNOWN
Classifier: Environment :: Console
Classifier: Intended Audience :: Developers
Classifier: License :: OSI Approved :: MIT License
Classifier: Programming Language :: Python :: 2.7
Classifier: Natural Language :: English
Classifier: Topic :: Software Development :: Version Control
